<?xml version="1.0" encoding="UTF-8"?>
<site-conf xmlns:xsi="http://www.w3.org/2001/XMLSchema-instance"
        xsi:noNamespaceSchemaLocation="http://ofbiz.apache.org/dtds/site-conf.xsd">
    <include location="component://common/webcommon/WEB-INF/common-controller.xml"/>

    <description>CRM Campaign Component Site Configuration File</description>
    
    <request-map uri="ListCallCampaign">
		<security https="true" auth="true" />
		<response name="success" type="view" value="ListCallCampaign" />
	</request-map>
	
    <request-map uri="ImportDataFromExcel">
		<security https="true" auth="true" />
		<response name="success" type="view" value="ImportDataFromExcel" />
	</request-map>
	
	<request-map uri="CreateCallCampaign">
		<security https="true" auth="true" />
		<response name="success" type="view" value="CreateCallCampaign" />
	</request-map>
    
    <request-map uri="uploadExcelDocument">
		<security https="true" auth="true" />
		<event type="service" invoke="uploadExcelDocument"/>
		<response name="success" type="request" value="json"></response>
        <response name="error" type="request" value="json"></response>
	</request-map>
    <request-map uri="importCustomer">
		<security https="true" auth="true" />
		<event type="service" invoke="importCustomer"/>
		<response name="success" type="request" value="json"></response>
        <response name="error" type="request" value="json"></response>
	</request-map>
    <request-map uri="updateTempCustomer">
		<security https="true" auth="true" />
		<event type="service" invoke="updateTempCustomer"/>
		<response name="success" type="request" value="json"></response>
        <response name="error" type="request" value="json"></response>
	</request-map>
    <request-map uri="deleteTempCustomer">
		<security https="true" auth="true" />
		<event type="service" invoke="deleteTempCustomer"/>
		<response name="success" type="request" value="json"></response>
        <response name="error" type="request" value="json"></response>
	</request-map>
    <request-map uri="deleteAllTempCustomer">
		<security https="true" auth="true" />
		<event type="service" invoke="deleteAllTempCustomer"/>
		<response name="success" type="request" value="json"></response>
        <response name="error" type="request" value="json"></response>
	</request-map>
    
    <request-map uri="checkCampaignExist">
		<security https="true" auth="true" />
		<event type="service" invoke="checkCampaignExist"/>
		<response name="success" type="request" value="json"></response>
        <response name="error" type="request" value="json"></response>
	</request-map>
    
    <request-map uri="getCallCenterEmployee">
		<security https="true" auth="true" />
		<event type="service" invoke="getCallCenterEmployee"/>
		<response name="success" type="request" value="json"></response>
        <response name="error" type="request" value="json"></response>
	</request-map>
    
    <request-map uri="createCallCampaignAndContact">
		<security https="true" auth="true" />
		<event type="service" invoke="createCallCampaignAndContact"/>
		<response name="success" type="request" value="json"></response>
        <response name="error" type="request" value="json"></response>
	</request-map>
    <request-map uri="updateCallCampaignAndContact">
		<security https="true" auth="true" />
		<event type="service" invoke="updateCallCampaignAndContact"/>
		<response name="success" type="request" value="json"></response>
        <response name="error" type="request" value="json"></response>
	</request-map>
    <request-map uri="removeCallCampaign">
		<security https="true" auth="true" />
		<event type="service" invoke="removeCallCampaign"/>
		<response name="success" type="request" value="json"></response>
        <response name="error" type="request" value="json"></response>
	</request-map>
    
    <request-map uri="loadCampaignTerms">
		<security https="true" auth="true" />
		<event type="service" invoke="loadCampaignTerms"/>
		<response name="success" type="request" value="json"></response>
        <response name="error" type="request" value="json"></response>
	</request-map>
    <request-map uri="saveCampaignTerms">
		<security https="true" auth="true" />
		<event type="service" invoke="saveCampaignTerms"/>
		<response name="success" type="request" value="json"></response>
        <response name="error" type="request" value="json"></response>
	</request-map>
	
	<request-map uri="autoAssignContact">
		<security https="true" auth="true" />
		<event type="service" invoke="autoAssignContact"/>
		<response name="success" type="request" value="json"></response>
        <response name="error" type="request" value="json"></response>
	</request-map>
	<request-map uri="assignContactToParty">
		<security https="true" auth="true" />
		<event type="service" invoke="assignContactToParty"/>
		<response name="success" type="request" value="json"></response>
        <response name="error" type="request" value="json"></response>
	</request-map>
	<request-map uri="unassignContactToParty">
		<security https="true" auth="true" />
		<event type="service" invoke="unassignContactToParty"/>
		<response name="success" type="request" value="json"></response>
        <response name="error" type="request" value="json"></response>
	</request-map>
	
	<request-map uri="getContactCampaignReport">
		<security https="true" auth="true" />
		<event type="service" invoke="getContactCampaignReport"/>
		<response name="success" type="request" value="json"></response>
        <response name="error" type="request" value="json"></response>
	</request-map>

    <request-map uri="getDataResources">
		<security https="true" auth="true" />
		<event type="service" invoke="getDataResources"/>
		<response name="success" type="request" value="json"></response>
        <response name="error" type="request" value="json"></response>
	</request-map>
	<request-map uri="checkDataHasAssigned">
		<security https="true" auth="true" />
		<event type="service" invoke="checkDataHasAssigned"/>
		<response name="success" type="request" value="json"></response>
        <response name="error" type="request" value="json"></response>
	</request-map>
	<request-map uri="moveDataCustomer">
		<security https="true" auth="true" />
		<event type="service" invoke="moveDataCustomer"/>
		<response name="success" type="request" value="json"></response>
        <response name="error" type="request" value="json"></response>
	</request-map>
    <view-map name="CreateCallCampaign" type="screen" page="component://basecrm/widget/BaseCRMCampaignScreens.xml#CreateCallCampaign"/>
    <view-map name="ListCallCampaign" type="screen" page="component://basecrm/widget/BaseCRMCampaignScreens.xml#ListCallCampaign"/>
    <view-map name="ImportDataFromExcel" type="screen" page="component://basecrm/widget/BaseCRMCampaignScreens.xml#ImportDataFromExcel"/>
</site-conf>