<forms xmlns:xsi="http://www.w3.org/2001/XMLSchema-instance"
	xsi:noNamespaceSchemaLocation="http://ofbiz.apache.org/dtds/widget-form.xsd">
	<form name="ListSkillTypes" type="multi" title="" target="updateSkillType"
		odd-row-style="alternate-row" header-row-style="header-row-2"
		default-table-style="table table-striped table-hover table-bordered dataTable" paginate-target="EditSkillTypes" style="abc">
		<actions>
			<entity-condition entity-name="SkillType">
				<order-by field-name="skillTypeId" />
			</entity-condition>
		</actions>
		<auto-fields-service service-name="updateSkillType"
			default-field-type="hidden" />
		<field name="skillTypeId" title="${uiLabelMap.CommonId}">
			<display />
		</field>
		<field name="description" title="${uiLabelMap.CommonDescription}">
			<text />
		</field>
		<field name="deleteLink" title="${uiLabelMap.CommonDelete}"
			widget-style="btn btn-mini btn-danger icon-trash" >
			<hyperlink target="deleteSkillType" description=" "
				also-hidden="false" confirmation-message="${uiLabelMap.NotifyDelete}" request-confirmation="true">
				<parameter param-name="skillTypeId" />
			</hyperlink>
		</field>
		<field name="_rowSubmit" title="${uiLabelMap.CommonSelect}">
			<hidden value="Y" />
		</field>
		<field name="submitButton" title="${uiLabelMap.CommonUpdate}"
			widget-style="btn btn-small btn-primary">
			<submit button-type="button" image-location="icon-ok" />
		</field>
	</form>
	
	<form name="AddJobInterviewType" type="single" target="createJobInterviewType" header-row-style="header-row" default-table-style="basic-table">
        <field name="jobInterviewTypeId" title="${uiLabelMap.CommonId}" required-field="true" title-style="asterisk"><text/></field>
        <field name="description" title="${uiLabelMap.CommonDescription}" title-style="asterisk" required-field="true"><text/></field>
        <field name="submitButton" title="${uiLabelMap.CommonCreate}" widget-style="btn btn-small btn-primary"><submit button-type="button" image-location="icon-ok"/></field>
    </form>
	
	<form name="ListJobInterviewType" type="multi" target="updateJobInterviewType" odd-row-style="alternate-row" header-row-style="header-row-2"
        default-table-style="table table-striped table-hover table-bordered dataTable" paginate-target="EditJobInterviewType">
        <actions>
            <entity-condition entity-name="JobInterviewType"><order-by field-name="jobInterviewTypeId"/></entity-condition>
        </actions>
        <field name="jobInterviewTypeId" title="${uiLabelMap.CommonId}"><display/></field>
        <field name="description" title="${uiLabelMap.CommonDescription}"><text/></field>
        <field name="deleteLink" title="${uiLabelMap.CommonDelete}" widget-style="btn btn-mini btn-danger icon-trash ">
            <hyperlink also-hidden="false" description=" " target="deleteJobInterviewType" confirmation-message="${uiLabelMap.NotifyDelete}" request-confirmation="true"> 
                <parameter param-name="jobInterviewTypeId"/> 
            </hyperlink>
        </field>
        <field name="_rowSubmit" title="${uiLabelMap.CommonSelect}"><hidden value="Y"/></field>
        <field name="submitButton" title="${uiLabelMap.CommonUpdate}" widget-style="btn btn-small btn-primary btn-position-center"><submit button-type="button" image-location="icon-ok"/></field>
    </form>
	
	<form name="AddSkillType" type="single" target="createSkillType"
		default-map-name="skillType" header-row-style="header-row"
		default-table-style="basic-table">
		<auto-fields-service service-name="createSkillType"
			default-field-type="hidden" />
		<field name="skillTypeId" title="${uiLabelMap.CommonId}" title-style="asterisk" required-field="true">
			<text />
		</field>
		<field name="description" title="${uiLabelMap.CommonDescription}"
			title-style="asterisk" required-field="true">
			<text />
		</field>
		<field name="submitButton" title="${uiLabelMap.CommonCreate}"
			widget-style="btn btn-small btn-primary">
			<submit button-type="button" image-location="icon-ok" />
		</field>
	</form>

	<form name="ListQualificationTypes" type="multi" title=""
		target="updateQualificationType" odd-row-style="alternate-row"
		header-row-style="header-row-2"
		default-table-style="table table-striped table-hover table-bordered dataTable">
		<actions>
			<entity-condition entity-name="PartyQualType">
				<condition-expr field-name="parentTypeId" operator="equals" value="DEGREE"/>
				<order-by field-name="partyQualTypeId" />
			</entity-condition>
		</actions>
		<auto-fields-service service-name="updateQualificationType"
			default-field-type="hidden" />
		<field name="partyQualTypeId" title="${uiLabelMap.CommonId}">
			<display />
		</field>
		<field name="description" title="${uiLabelMap.CommonDescription}">
			<text />
		</field>
		<field name="deleteLink" title="${uiLabelMap.CommonDelete}"
			widget-style="btn btn-mini btn-danger icon-trash">
			<hyperlink target="deleteQualificationType" description=" "
				also-hidden="false" confirmation-message="${uiLabelMap.NotifyDelete}" request-confirmation="true">
				<parameter param-name="partyQualTypeId" />
			</hyperlink>
		</field>
		<field name="_rowSubmit" title="${uiLabelMap.CommonSelect}">
			<hidden value="Y" />
		</field>
		<field name="submitButton" title="${uiLabelMap.CommonUpdate}"
			widget-style="btn btn-small btn-primary">
			<submit button-type="button" image-location="icon-ok" />
		</field>
	</form>

	<form name="AddQualificationType" type="single" target="createQualificationType"
		default-map-name="partyQualType" header-row-style="header-row"
		default-table-style="basic-table">
		<auto-fields-service service-name="createQualificationType"
			default-field-type="hidden" />
		<field name="partyQualTypeId" title="${uiLabelMap.CommonId}" required-field="true" title-style="asterisk">
			<text />
		</field>
		<field name="parentTypeId">
			<hidden value="DEGREE" />
		</field>
		<field name="description" title="${uiLabelMap.CommonDescription}"
			title-style="asterisk" required-field="true">
			<text />
		</field>
		<field name="submitButton" title="${uiLabelMap.CommonCreate}"
			widget-style="btn btn-small btn-primary">
			<submit button-type="button" image-location="icon-ok" />
		</field>
	</form>

	<form name="ListExamTypes" type="multi" title="" target="updateExamType"
		odd-row-style="alternate-row" header-row-style="header-row-2"
		default-table-style="table table-striped table-hover table-bordered dataTable">
		<actions>
			<entity-condition entity-name="Enumeration">
				<condition-expr field-name="enumTypeId" operator="equals"
					value="EXAM_TYPE" />
				<order-by field-name="enumId" />
			</entity-condition>
		</actions>
		<auto-fields-service service-name="updateExamType"
			default-field-type="hidden" />
		<field name="enumId" title="${uiLabelMap.CommonId}">
			<display />
		</field>
		<field name="description" title="${uiLabelMap.CommonDescription}">
			<text />
		</field>
		<field name="deleteLink" title="${uiLabelMap.CommonDelete}"
			widget-style="btn btn-mini btn-danger icon-trash">
			<hyperlink target="deleteExamType" description=" "
				also-hidden="false" confirmation-message="${uiLabelMap.NotifyDelete}" request-confirmation="true">
				<parameter param-name="enumId" />
			</hyperlink>
		</field>
		<field name="_rowSubmit" title="${uiLabelMap.CommonSelect}">
			<hidden value="Y" />
		</field>
		<field name="submitButton" title="${uiLabelMap.CommonUpdate}"
			widget-style="btn btn-small btn-primary">
			<submit button-type="button" image-location="icon-ok" />
		</field>
	</form>

	<form name="AddExamType" type="single" target="createExamType"
		default-map-name="enumeration" header-row-style="header-row"
		default-table-style="basic-table">
		<auto-fields-service service-name="createExamType"
			default-field-type="hidden" />
		<field name="enumId" title="${uiLabelMap.CommonId}" required-field="true" title-style="asterisk">
			<text />
		</field>
		<field name="enumTypeId">
			<hidden value="EXAM_TYPE" />
		</field>
		<field name="description" title="${uiLabelMap.CommonDescription}"
			title-style="asterisk" required-field="true">
			<text />
		</field>
		<field name="submitButton" title="${uiLabelMap.CommonCreate}"
			widget-style="btn btn-small btn-primary">
			<submit button-type="button" image-location="icon-ok" />
		</field>
	</form>
	
	<form name="AddEmplLeaveType" type="single" target="createEmplLeaveType" default-map-name="emplLeaveType"
        header-row-style="header-row" default-table-style="basic-table">
        <auto-fields-service service-name="createEmplLeaveType" default-field-type="hidden"/>
        <field name="leaveTypeId" title="${uiLabelMap.CommonId}" required-field="true" title-style="asterisk"><text/></field>
        <field name="description" title="${uiLabelMap.CommonDescription}" required-field="true" title-style="asterisk"><text/></field>
        <field name="submitButton" title="${uiLabelMap.CommonCreate}" widget-style="btn btn-small btn-primary"><submit button-type="button" image-location="icon-ok"/></field>
    </form>
    
    <form name="ListEmplLeaveTypes" type="multi" title="" target="updateEmplLeaveType"
        odd-row-style="alternate-row" header-row-style="header-row-2" default-table-style="table table-striped table-hover table-bordered dataTable">
        <actions>
            <entity-condition entity-name="EmplLeaveType"><order-by field-name="leaveTypeId"/></entity-condition>
        </actions>
        <auto-fields-service service-name="updateEmplLeaveType" default-field-type="hidden"/>
        <field name="leaveTypeId" title="${uiLabelMap.CommonId}"><display/></field>
        <field name="description" title="${uiLabelMap.CommonDescription}"><text/></field>
        <field name="deleteLink" title="${uiLabelMap.CommonDelete}" widget-style="btn btn-mini btn-danger icon-trash">
            <hyperlink target="deleteEmplLeaveType" description=" " also-hidden="false" confirmation-message="${uiLabelMap.NotifyDelete}" request-confirmation="true">
                <parameter param-name="leaveTypeId"/>
            </hyperlink>
        </field>
        <field name="_rowSubmit" title="${uiLabelMap.CommonSelect}"><hidden value="Y"/></field>
        <field name="submitButton" title="${uiLabelMap.CommonUpdate}" widget-style="btn btn-small btn-primary btn-position-center"><submit button-type="button" image-location="icon-ok"/></field>
    </form>
    
    <form name="AddEmplLeaveReasonType" type="single" target="createEmplLeaveReasonType" default-map-name="emplLeaveReasonType"
        header-row-style="header-row" default-table-style="basic-table">
        <auto-fields-service service-name="createEmplLeaveReasonType" default-field-type="hidden"/>
        <field name="emplLeaveReasonTypeId" title="${uiLabelMap.CommonId}" required-field="true" title-style="asterisk"><text/></field>
        <field name="description" title="${uiLabelMap.CommonDescription}" title-style="asterisk" required-field="true"><text/></field>
        <field name="submitButton" title="${uiLabelMap.CommonCreate}" widget-style="btn btn-small btn-primary"><submit button-type="button" image-location="icon-ok"/></field>
    </form>
    <form name="ListEmplLeaveReasonTypes" type="multi" target="updateEmplLeaveReasonType"
        odd-row-style="alternate-row" header-row-style="header-row-2" list-name="emplLeaveList"
        default-table-style="table table-striped table-hover table-bordered dataTable">
        <actions>
        	<entity-condition entity-name="EmplLeaveReasonType" list="emplLeaveList">
           		<order-by field-name="emplLeaveReasonTypeId"/>
           	</entity-condition>    
        </actions>
       <!--  <auto-fields-service service-name="updateEmplLeaveReasonType" default-field-type="hidden"/> -->
        <field name="emplLeaveReasonTypeId" title="${uiLabelMap.CommonId}"><display/></field>
        <field name="description" title="${uiLabelMap.CommonDescription}">
        	<text/>
       	</field>
        <field name="deleteLink" title="${uiLabelMap.CommonDelete}" 
        	widget-style="btn btn-mini btn-danger icon-trash">
            <hyperlink target="deleteEmplLeaveReasonType" description=" " also-hidden="false" confirmation-message="${uiLabelMap.NotifyDelete}" request-confirmation="true">
                <parameter param-name="emplLeaveReasonTypeId"/>
            </hyperlink>
        </field>
        <field name="_rowSubmit" title="${uiLabelMap.CommonSelect}"><hidden value="Y"/></field>
        <field name="submitButton" title="${uiLabelMap.CommonUpdate}" widget-style="btn btn-small btn-primary btn-position-center"><submit button-type="button" image-location="icon-ok"/></field>
    </form>
    
    <form name="FindEmplPositionTypes" type="single" header-row-style="header-row" default-table-style="basic-table">
        <auto-fields-entity entity-name="EmplPositionType" default-field-type="find"/>
        <field name="noConditionFind"><hidden value="Y"/><!-- if this isn't there then with all fields empty no query will be done --></field>
        <field name="emplPositionTypeId">
            <drop-down allow-empty="true">
                <entity-options entity-name="EmplPositionType" description="${description}" key-field-name="emplPositionTypeId"/>
            </drop-down>
        </field>
        <field name="description" title="${uiLabelMap.CommonDescription}"><text/></field>
        <field name="searchButton" title="${uiLabelMap.CommonFind}" widget-style="btn btn-small btn-primary"><submit button-type="button" image-location="icon-search"/></field>
    </form>
    
    <form name="ListEmplPositionTypes" type="list" list-name="listIt" target="updateEmplPositionType"
        odd-row-style="alternate-row" header-row-style="header-row-2" default-table-style="table table-striped table-hover table-bordered dataTable">
        <actions>
            <service service-name="performFind" result-map="result" result-map-list="listIt">
                <field-map field-name="inputFields" from-field="emplPositionTypeCtx"/>
                <field-map field-name="entityName" value="EmplPositionType"/>
                <field-map field-name="viewIndex" from-field="viewIndex"/>
                <field-map field-name="viewSize" from-field="viewSize"/>
                <field-map field-name="noConditionFind" value="Y"/>
            </service>
        </actions>
        <auto-fields-service service-name="updateEmplPositionType" default-field-type="hidden"/>
        <field name="emplPositionTypeId" title="${uiLabelMap.HumanResEmplPositionType}" widget-style="">
            <hyperlink also-hidden="false" description="${emplPositionTypeId}" target="EditEmplPositionTypes">
                <parameter param-name="emplPositionTypeId"/>
            </hyperlink>
        </field>
        <field name="description" title="${uiLabelMap.CommonDescription}"><display/></field>
        <field name="deleteLink" title="${uiLabelMap.CommonDelete}" widget-style="btn btn-mini btn-danger  icon-trash align-center">
            <hyperlink target="deleteEmplPositionType" description=" " also-hidden="false" confirmation-message="${uiLabelMap.NotifyDelete}" request-confirmation="true">
                <parameter param-name="emplPositionTypeId"/>
            </hyperlink>
        </field>
    </form>
    
    <form name="EditEmplPositionTypes" type="single" target="updateEmplPositionType" default-map-name="emplPositionType"
        header-row-style="header-row" default-table-style="basic-table">
        <alt-target use-when="emplPositionType==null" target="createEmplPositionType"/>
        <auto-fields-service service-name="updateEmplPositionType"/>
        <field name="emplPositionTypeId" use-when="emplPositionType==null"><text/></field>
        <field name="emplPositionTypeId" use-when="emplPositionType!=null"><display/></field>
        <field name="description" title="${uiLabelMap.CommonDescription}" required-field="true" title-style="asterisk"><text/></field>
        <field name="dayLeaveRegulation" title="${uiLabelMap.DayLeaveRegulation}"><text></text></field>
        <field name="submitButton" title="${uiLabelMap.CommonCreate}" widget-style="btn btn-small btn-primary"><submit button-type="button" image-location="icon-ok"/></field>
        <field name="submitButton" title="${uiLabelMap.CommonUpdate}" use-when="emplPositionType!=null" widget-style="btn btn-small btn-primary"><submit button-type="button" image-location="icon-ok"/></field>
    </form>
    
    <form name="ListEmplPositionTypeRates" type="list" title="" target="deleteEmplPositionTypeRate"
        odd-row-style="alternate-row" header-row-style="header-row-2" default-table-style="table table-striped table-hover table-bordered dataTable">
        <actions>
            <set field="nowDate" value="${bsh:org.ofbiz.base.util.UtilDateTime.nowDateString(&quot;yyyy-MM-dd HH:mm:ss.S&quot;)}" type="String"/>
            <entity-condition entity-name="EmplPositionTypeRateAndAmount" filter-by-date="true">
                <condition-list combine="and">
                    <condition-expr field-name="emplPositionTypeId" from-field="parameters.emplPositionTypeId" operator="equals"/>
                    <condition-list combine="or">
                        <condition-expr field-name="rateAmountFromDate" from-field="null" operator="equals"/>
                        <condition-expr field-name="rateAmountFromDate" from-field="nowDate" operator="less"/>
                    </condition-list>
                    <condition-list combine="or">
                        <condition-expr field-name="rateAmountThruDate" from-field="null" operator="equals"/>
                        <condition-expr field-name="rateAmountThruDate" from-field="nowDate" operator="greater"/>
                    </condition-list>
                </condition-list>
                <order-by field-name="rateTypeId"/>
            </entity-condition>
        </actions>
        <field name="rateCurrencyUomId"><hidden/></field>
        <field name="emplPositionTypeId"><hidden/></field>
        <field name="fromDate"><hidden/></field>
        <field name="rateAmountFromDate"><hidden/></field>
        <field name="rateTypeId"><display-entity entity-name="RateType" description="${description}"/></field>
        <field name="periodTypeId"><display-entity entity-name="PeriodType" description="${description}"/></field>
        <field name="payGradeId"><display-entity entity-name="PayGrade" description="${description}"/></field>
        <field name="salaryStepSeqId" title="${uiLabelMap.HROlbiusSalaryStepSeqId}"><display/></field>
        <field name="rateAmount"><display type="currency" currency="${rateCurrencyUomId}"/></field>
        <field name="deleteButton" widget-style="btn btn-small btn-danger"><submit button-type="button" image-location="icon-trash"/></field>
    </form>
    <form name="AddEmplPositionTypeRate" type="single" target="updateEmplPositionTypeRate" default-map-name="emplPositionTypeRate" paginate-target="EditEmplPositionTypeRates"
        header-row-style="header-row" default-table-style="basic-table">
        <actions>
            <property-to-field field="defaultCurrencyUomId" resource="general" property="currency.uom.id.default" default="USD"/>
        </actions>
        <field name="emplPositionTypeId"><hidden value="${parameters.emplPositionTypeId}"/></field>
        <field name="rateTypeId"   tooltip="${uiLabelMap.CommonRequired}" widget-style="required">
            <drop-down>
                <entity-options description="${description}" key-field-name="rateTypeId" entity-name="RateType">
                    <entity-order-by field-name="description"/>
                </entity-options>
            </drop-down>
        </field>
        <field name="payGradeId" position="2"><lookup target-form-name="LookupPayGrade"/></field>
        <field name="periodTypeId" tooltip="${uiLabelMap.CommonRequired}" widget-style="required">
            <drop-down allow-empty="false" no-current-selected-key="RATE_MONTH">
                <entity-options description="${description}" key-field-name="periodTypeId" entity-name="PeriodType">
                    <entity-order-by field-name="periodTypeId"/>
                </entity-options>
            </drop-down>
        </field>
        <field name="salaryStepSeqId" title="${uiLabelMap.HROlbiusSalaryStepSeqId}" position="2"><lookup target-form-name="LookupSalaryStep"/></field>
        <field name="rateAmount"><text/></field>
        <field name="rateCurrencyUomId" position="2">
            <drop-down allow-empty="true" no-current-selected-key="${defaultOrganizationPartyCurrencyUomId}">
                <entity-options key-field-name="uomId" description="${description} - ${abbreviation}" entity-name="Uom">
                    <entity-constraint name="uomTypeId" operator="equals" value="CURRENCY_MEASURE"/>
                    <entity-order-by field-name="description"/>
                </entity-options>
            </drop-down>
        </field>
        <field name="submitButton" title="${uiLabelMap.CommonCreate}" widget-style="btn btn-small btn-primary"><submit button-type="button" image-location="icon-ok"/></field>
    </form>
    
    <form name="FindPayGrades" type="single" target="FindPayGrades" title=""
        header-row-style="header-row" default-table-style="basic-table">
        <auto-fields-service service-name="createPayGrade" default-field-type="find"/>
        <field name="noConditionFind"><hidden value="Y"/><!-- if this isn't there then with all fields empty no query will be done --></field>
        <field name="payGradeId"><lookup target-form-name="LookupPayGrade"/></field>
        <field name="searchButton" title="${uiLabelMap.CommonFind}" widget-style="btn btn-small btn-primary"><submit button-type="button" image-location="icon-search"/></field>
    </form>
    
    <form name="ListPayGrades" type="list" list-name="listIt" title="" target="updatePayGrade" paginate-target="FindPayGrades"
        odd-row-style="alternate-row" header-row-style="header-row-2" default-table-style="table table-striped table-hover table-bordered dataTable">
        <actions>
            <service service-name="performFind" result-map="result" result-map-list="listIt">
                <field-map field-name="inputFields" from-field="payGradeCtx"/>
                <field-map field-name="entityName" value="PayGrade"/>
                <field-map field-name="viewIndex" from-field="viewIndex"/>
                <field-map field-name="viewSize" from-field="viewSize"/>
                <field-map field-name="noConditionFind" value="Y"/>
            </service>
        </actions>
        <auto-fields-service default-field-type="display" service-name="updatePayGrade"/>
        <field name="payGradeId" title="${uiLabelMap.HumanResPayGradeID}" widget-style="">
            <hyperlink also-hidden="true" target="EditPayGrade" target-type="plain" description="${payGradeId}">
                <parameter param-name="payGradeId"/>
            </hyperlink>
        </field>
        <field name="deleteLink" title="${uiLabelMap.CommonDelete}" widget-style="btn btn-danger btn-mini btn-position icon-trash">
            <hyperlink target="deletePayGrade" description=" " also-hidden="false" confirmation-message="${uiLabelMap.NotifyDelete}" request-confirmation="true">
                <parameter param-name="payGradeId"/>
            </hyperlink>
        </field>
    </form>
    
    <form name="EditPayGrade" type="single" target="updatePayGrade" title=""
        header-row-style="header-row" default-table-style="basic-table" default-map-name="payGrade">
        <alt-target use-when="payGradeId==null" target="createPayGrade"/>
        <auto-fields-service service-name="updatePayGrade"/>
        <field use-when="payGrade!=null" name="payGradeId"  title="${uiLabelMap.CommonId}" tooltip="${uiLabelMap.CommonNotModifRecreat}" title-style="asterisk" required-field="true"><display/></field>
        <field use-when="payGrade==null" name="payGradeId" title="${uiLabelMap.CommonId}" title-style="asterisk" required-field="true"><text/></field>
        <field name="payGradeName" title-style="asterisk" required-field="true"><text/></field>
        <field name="submitButton" title="${uiLabelMap.CommonCreate}" widget-style="btn btn-small btn-primary"><submit button-type="button" image-location="icon-ok"/></field>
        <field name="submitButton" title="${uiLabelMap.CommonUpdate}" use-when="payGrade!=null" widget-style="btn btn-small btn-primary"><submit button-type="button" image-location="icon-ok"/></field>
    </form>
    
<!--     <form name="ListSalarySteps" type="multi" target="updateSalaryStep?salaryStepSeqId=${salaryStepSeqId}&amp;payGradeId=${payGradeId}" paginate-target="findSalarySteps" -->
<!--         odd-row-style="alternate-row" header-row-style="header-row-2" default-table-style="table table-striped table-hover table-bordered dataTable"> -->
<!--         <actions> -->
<!--             <entity-one entity-name="SalaryStep" auto-field-map="true"/> -->
<!--             <entity-condition entity-name="SalaryStep"> <condition-expr field-name="payGradeId" operator="equals" from-field="payGradeId"/><order-by field-name="salaryStepSeqId"/></entity-condition> -->
<!--         </actions> -->
<!--         <auto-fields-service service-name="updateSalaryStep"/> -->
<!--         <field name="salaryStepSeqId" title="${uiLabelMap.HROlbiusSalaryStepSeqId}"><display also-hidden="true"/></field> -->
<!--         <field name="payGradeId"><hidden/></field> -->
<!--         <field name="_rowSubmit" title="${uiLabelMap.CommonSelect}"><hidden value="Y"/></field> -->
<!--         <field name="submitButton" title="${uiLabelMap.CommonUpdate}" widget-style="btn btn-small btn-primary btn-position-center"><submit button-type="button" image-location="icon-ok"/></field> -->
<!--         <field name="deleteLink" title=" " widget-style="btn btn-danger btn-mini icon-trash open-sans"> -->
<!--             <hyperlink target="deleteSalaryStep" description=" " confirmation-message="${uiLabelMap.NotifyDelete}" request-confirmation="true"> -->
<!--                 <parameter param-name="salaryStepSeqId"/> -->
<!--                 <parameter param-name="payGradeId"/> -->
<!--             </hyperlink> -->
<!--         </field> -->
<!--     </form> -->
    
    <form name="AddSalaryStep" type="single" target="createSalaryStep"
        header-row-style="header-row" default-table-style="basic-table">
        <auto-fields-service service-name="createSalaryStep"/>
        <field name="salaryStepSeqId"><ignored/></field>
        <field name="payGradeId"><hidden/></field>
        <field name="dateModified" title-style="asterisk" required-field="true"><date-time default-value="${nowTimestamp}" /></field>
        <field name="amount" title="${uiLabelMap.HrolbiusAmountSalary}" title-style="asterisk" required-field="true"></field>
        <field name="submitButton" title="${uiLabelMap.CommonCreate}" widget-style="btn btn-small btn-primary"><submit button-type="button" image-location="icon-ok"/></field>
    </form>
    
    <form name="ListSalarySteps" type="multi" target="updateSalaryStep?salaryStepSeqId=${salaryStepSeqId}&amp;payGradeId=${payGradeId}" paginate-target="EditSalarySteps"
        odd-row-style="alternate-row" header-row-style="header-row-2" default-table-style="table table-striped table-hover table-bordered dataTable">
        <actions>
            <entity-one entity-name="SalaryStep" auto-field-map="true"/>
            <entity-condition entity-name="SalaryStep"> <condition-expr field-name="payGradeId" operator="equals" from-field="payGradeId"/><order-by field-name="salaryStepSeqId"/></entity-condition>
        </actions>
        <auto-fields-service service-name="updateSalaryStep"/>
        <field name="salaryStepSeqId" title="${uiLabelMap.HROlbiusSalaryStepSeqId}"><display also-hidden="true"/></field>
        <field name="payGradeId"><hidden/></field>
        <field name="amount" title="${uiLabelMap.HrolbiusAmountSalary}"><display></display></field>
        <field name="_rowSubmit" title="${uiLabelMap.CommonSelect}"><hidden value="Y"/></field>
        <field name="submitButton" title="${uiLabelMap.CommonUpdate}" widget-style="btn btn-small btn-primary btn-position-center"><submit button-type="button" image-location="icon-ok"/></field>
        <field name="deleteLink" title=" " widget-style="btn btn-danger btn-mini icon-trash">
            <hyperlink target="deleteSalaryStep" description=" " confirmation-message="${uiLabelMap.NotifyDelete}" request-confirmation="true">
                <parameter param-name="salaryStepSeqId"/>
                <parameter param-name="payGradeId"/>
            </hyperlink>
        </field>
    </form>
    
    <form name="AddSalaryStep" type="single" target="createSalaryStep"
        header-row-style="header-row" default-table-style="basic-table">
        <auto-fields-service service-name="createSalaryStep"/>
        <field name="salaryStepSeqId"><ignored/></field>
        <field name="payGradeId"><hidden/></field>
        <field name="submitButton" title="${uiLabelMap.CommonCreate}" widget-style="btn btn-small btn-primary"><submit button-type="button" image-location="icon-ok"/></field>
    </form>
    
    <form name="FindPerfReviewItemType" type="single" target="FindPerfReviewItemType" title=""
        header-row-style="header-row" default-table-style="basic-table">
        <auto-fields-entity entity-name="PerfReviewItemType" default-field-type="find" />
        <field name="noConditionFind"><hidden value="Y"/><!-- if this isn't there then with all fields empty no query will be done --></field>
        <field name="searchButton" title="${uiLabelMap.CommonFind}" widget-style="btn btn-small btn-primary"><submit button-type="button" image-location="icon-search"/></field>
    </form>
    
    <form name="ListPerfReviewItemType" type="list" list-name="listIt" title=""
        odd-row-style="alternate-row" header-row-style="header-row-2" default-table-style="table table-striped table-hover table-bordered dataTable" paginate-target="FindPerfReviewItemType">
        <actions>
            <service service-name="performFind" result-map="result" result-map-list="listIt">
                <field-map field-name="inputFields" from-field="requestParameters"/>
                <field-map field-name="entityName" value="PerfReviewItemType"/>
                <field-map field-name="viewIndex" from-field="viewIndex"/>
                <field-map field-name="viewSize" from-field="viewSize"/>
                <field-map field-name="noConditionFind" value="Y"/>
            </service>
        </actions>
        <auto-fields-entity entity-name="PerfReviewItemType" default-field-type="display"/>
        <field name="emplPositionTypeId"> 
        	<display-entity entity-name="EmplPositionType" key-field-name="emplPositionTypeId" description="${description}" ></display-entity>
        </field>
        <field name="weight" title="${uiLabelMap.jobWeight}"></field>
        <field name="_editLink" title="${uiLabelMap.CommonUpdate}" widget-style="icon-edit" widget-area-style="textcenter-imp">
        	<hyperlink target-type="inter-app" description=" " id="EditPerfReviewItemType" style="icon-edit textcenter-imp" url-mode="inter-app" target="javascript:void(0);">
        	</hyperlink>
        </field>
    </form>
    
    <form name="EditPerfReviewItemType" type="single" target="createPerfReviewItemType" title=""
        header-row-style="header-row" default-table-style="basic-table">
        <auto-fields-service service-name="createPerfReviewItemType"/>
        <field name="parentTypeId">
        	<hidden />
        </field>
        <field name="hasTable">
        	<hidden value="N"/>
        </field>
        <field name="perfReviewItemTypeId" required-field="true" title-style="asterisk" title="${uiLabelMap.CommonId}"> 
        </field>
        <field name="emplPositionTypeId" >
        	<drop-down>
        		<entity-options description="${description}" entity-name="EmplPositionType"></entity-options>
        	</drop-down>
        </field>
        <field name="weight" title-style="asterisk" required-field="true" title="${uiLabelMap.jobWeight}"></field>
        <field name="fromDate" title-style="asterisk" required-field="true"><date-time/></field>
        <field name="thruDate" title-style="asterisk" required-field="true"><date-time/></field>
        <field name="submitButton" title="${uiLabelMap.CommonCreate}" widget-style="btn btn-small btn-primary"><submit button-type="button" image-location="icon-ok"/></field>
    </form>
    
    <form name="AddJobInterviewQuestionType" type="single" target="creatJobInterviewQuestionType" header-row-style="header-row" default-table-style="basic-table">
		<field name="questionTypeId" title="${uiLabelMap.CommonId}" required-field="true" title-style="asterisk"><text/></field>
	    <field name="description" title="${uiLabelMap.CommonDescription}" title-style="asterisk" required-field="true"><text/></field>
		<field name="submitButton" title="${uiLabelMap.CommonCreate}" widget-style="btn btn-small btn-primary"><submit button-type="button" image-location="icon-ok"/></field>
	</form>
	
	<form name="AddPeriodType" type="single" target="CreatePeriodType" header-row-style="header-row" default-table-style="basic-table">
		<auto-fields-entity entity-name="PeriodType" />
		<field name="periodTypeId" title="${uiLabelMap.CommonId}" title-style="asterisk" required-field="true"></field>
		<field name="description" title-style="asterisk" required-field="true"></field>
		<field name="uomId"><hidden value="TF_hr"/></field>
		<field name="periodLength" title="${uiLabelMap.HrolbiusPeriodLength}" title-style="asterisk" required-field="true"></field>
		<field name="submitButton" title="${uiLabelMap.CommonCreate}" widget-style="btn btn-small btn-primary"><submit button-type="button" image-location="icon-ok"/></field>
	</form>
	<form name="ListPeriodType" type="multi" target="UpdatePeriodType" odd-row-style="alternate-row" header-row-style="header-row-2"
        default-table-style="table table-striped table-hover table-bordered dataTable" separate-columns="true" group-columns="false"> 
        <actions>
        	<entity-condition entity-name="PeriodType"> <order-by field-name="periodTypeId"/></entity-condition>
        </actions>
        <auto-fields-entity entity-name="PeriodType" />
        <field name="periodTypeId" title="${uiLabelMap.CommonId}" ><display></display></field>
        <field name="description"><text></text></field>
        <field name="periodLength" title="${uiLabelMap.HrolbiusPeriodLength}"><text></text></field>
        <field name="uomId"><hidden/></field>
        <field name="deleteLink" title="${uiLabelMap.CommonDelete}" widget-style="btn btn-mini btn-danger icon-trash ">
        	<hyperlink target="DeletePeriodType" also-hidden="false" description=" " confirmation-message="${uiLabelMap.NotifyDelete}" request-confirmation="true">
        		<parameter param-name="periodTypeId"/>
        	</hyperlink>
        </field>
        <field name="_rowSubmit" title="${uiLabelMap.CommonSelect}"> <hidden value="Y"/></field>
        <field name="submitButton" title="${uiLabelMap.CommonUpdate}" widget-style="btn btn-small btn-primary"><submit button-type="button" image-location="icon-ok"/></field>
	</form>
	<!-- Training Class Type -->
	<form name="AddTrainingTypes" type="single" target="createTrainingTypes" header-row-style="header-row" default-table-style="basic-table">
        <field name="trainingClassTypeId" title="${uiLabelMap.CommonId}" title-style="asterisk" required-field="true"><text/></field>
        <field name="parentTypeId" title="${uiLabelMap.HRolbiusPreRequisiteSkill}"><lookup target-form-name="LookupTraining"/></field>
        <field name="description" title="${uiLabelMap.CommonDescription}" title-style="asterisk" required-field="true"><text/></field>
        <field name="submitButton" title="${uiLabelMap.CommonCreate}" widget-style="btn btn-small btn-primary"><submit button-type="button" image-location="icon-ok"/></field>
    </form>
    
    <form name="ListTrainingTypes" type="multi" title="" target="updateTrainingTypes" odd-row-style="alternate-row" header-row-style="header-row-2" 
        default-table-style="table table-striped table-hover table-bordered dataTable" separate-columns="true" group-columns="false">
        <actions>
            <entity-condition entity-name="TrainingClassType"><order-by field-name="trainingClassTypeId"/></entity-condition>
        </actions>
        <field name="trainingClassTypeId" title="${uiLabelMap.CommonId}" ><display/></field>
        <field name="parentTypeId" title="${uiLabelMap.HumanResPreRequisiteSkill}" widget-style="buttontext"><!-- <text/> --><lookup target-form-name="LookupTraining"/></field>
        <field name="description" title="${uiLabelMap.CommonDescription}"><text/></field>
        <field name="deleteLink" title="${uiLabelMap.CommonDelete}" widget-style="btn btn-mini btn-danger icon-trash ">
           <hyperlink also-hidden="false" description=" " target="deleteTrainingTypes" confirmation-message="${uiLabelMap.NotifyDelete}" request-confirmation="true"> 
                <parameter param-name="trainingClassTypeId"/> 
            </hyperlink>
        </field>
        <field name="_rowSubmit" title="${uiLabelMap.CommonSelect}"><hidden value="Y"/></field>

        <field name="submitButton" title="${uiLabelMap.CommonUpdate}" widget-style="btn btn-small btn-primary btn-position-center"><submit button-type="button" image-location="icon-ok"/></field>
    </form>   
    <!-- Recruitment Type -->  
    <form name="AddRecruitmentType" type="single" target="createRecruitmentType" header-row-style="header-row" default-table-style="basic-table">
    	<field name="recruitmentTypeId" title="${uiLabelMap.CommonId}" title-style="asterisk" required-field="true"><text/></field>
    	<field name="description" title="${uiLabelMap.HRolbiusRecruitmentTypeDescription}" title-style="asterisk" required-field="true"><text/></field>
    	<field name="submitButton" title="${uiLabelMap.CommonCreate}" widget-style="btn btn-small btn-primary"><submit button-type="button" image-location="icon-ok"/></field>
    </form>
    
    <form name="listRecruitmentTypes" type="multi" target="updateRecruitmentType" odd-row-style="alternate-row" header-row-style="header-row-2"
    	default-table-style="table table-striped table-hover table-bordered dataTable">
    	<actions>
    		<entity-condition entity-name="RecruitmentType"><order-by field-name="recruitmentTypeId"/></entity-condition>
    	</actions>
    <field name="recruitmentTypeId" title="${uiLabelMap.CommonId}" ><display/></field>
    <field name="description" title="${uiLabelMap.HRolbiusRecruitmentTypeDescription}"><text/></field>
   	<field name="deletelink" title="${uiLabelMap.CommonDelete}" widget-style="btn btn-mini btn-danger icon-trash">
   		<hyperlink target="deleteRecruitmentType" also-hidden="false" description=" " confirmation-message="${uiLabelMap.NotifyDelete}" request-confirmation="true">
   			<parameter param-name="recruitmentTypeId"/>
   		</hyperlink>
   	</field>
    <field name="submitButton" title="${uiLabelMap.CommonUpdate}" widget-style="btn btn-small btn-primary btn-position-center"><submit button-type="button" image-location="icon-ok"/></field>
    </form>
    
     <!-- Recruitment Form -->
     <form name="AddRecruitmentForm" type="single" target="createRecruitmentForm" header-row-style="header-row" default-table-style="basic-table">
    	<field name="recruitmentFormId" title="${uiLabelMap.CommonId}" title-style="asterisk" required-field="true"><text/></field>
    	<field name="description" title="${uiLabelMap.HRolbiusRecruitmentFormDescription}" title-style="asterisk" required-field="true"><text/></field>
    	<field name="submitButton" title="${uiLabelMap.CommonCreate}" widget-style="btn btn-small btn-primary"><submit button-type="button" image-location="icon-ok"/></field>
    </form>
    
    <form name="listRecruitmentForms" type="multi" target="updateRecruitmentForm" odd-row-style="alternate-row" header-row-style="header-row-2"
    	default-table-style="table table-striped table-hover table-bordered dataTable">
    	<actions>
    		<entity-condition entity-name="RecruitmentForm"><order-by field-name="recruitmentFormId"/></entity-condition>
    	</actions>
    <field name="recruitmentFormId" title="${uiLabelMap.CommonId}" ><display/></field>
    <field name="description" title="${uiLabelMap.HRolbiusRecruitmentFormDescription}"><text/></field>
   	<field name="deletelink" title="${uiLabelMap.CommonDelete}" widget-style="btn btn-mini btn-danger icon-trash">
   		<hyperlink target="deleteRecruitmentForm" also-hidden="false" description=" " confirmation-message="${uiLabelMap.NotifyDelete}" request-confirmation="true">
   			<parameter param-name="recruitmentFormId"/>
   		</hyperlink>
   	</field>
    <field name="submitButton" title="${uiLabelMap.CommonUpdate}" widget-style="btn btn-small btn-primary btn-position-center"><submit button-type="button" image-location="icon-ok"/></field>
    </form>
    
    <!-- Recruitment Criteria -->
     <form name="AddRecruitmentCriteria" type="single" target="createRecruitmentCriteria" header-row-style="header-row" default-table-style="basic-table">
    	<field name="recruitmentCriteriaId" title="${uiLabelMap.CommonId}" title-style="asterisk" required-field="true"><text/></field>
    	<field name="description" title="${uiLabelMap.HRolbiusRecruitmentCriteriaDescription}" title-style="asterisk" required-field="true"><text/></field>
    	<field name="submitButton" title="${uiLabelMap.CommonCreate}" widget-style="btn btn-small btn-primary"><submit button-type="button" image-location="icon-ok"/></field>
    </form>
     
    <form name="listRecruitmentCriterias" type="multi" target="updateRecruitmentCriteria" odd-row-style="alternate-row" header-row-style="header-row-2"
    	default-table-style="table table-striped table-hover table-bordered dataTable">
    	<actions>
    		<entity-condition entity-name="RecruitmentCriteria"><order-by field-name="recruitmentCriteriaId"/></entity-condition>
    	</actions>
    <field name="recruitmentCriteriaId" title="${uiLabelMap.CommonId}" ><display/></field>
    <field name="description" title="${uiLabelMap.HRolbiusRecruitmentCriteriaDescription}"><text/></field>
   	<field name="deletelink" title="${uiLabelMap.CommonDelete}" widget-style="btn btn-mini btn-danger icon-trash">
   		<hyperlink target="deleteRecruitmentCriteria" also-hidden="false" description=" " confirmation-message="${uiLabelMap.NotifyDelete}" request-confirmation="true">
   			<parameter param-name="recruitmentCriteriaId"/>
   		</hyperlink>
   	</field>
    <field name="submitButton" title="${uiLabelMap.CommonUpdate}" widget-style="btn btn-small btn-primary btn-position-center"><submit button-type="button" image-location="icon-ok"/></field>
    </form>
    
    <!-- Training Form -->
     <form name="AddTrainingForm" type="single" target="createTrainingForm" header-row-style="header-row" default-table-style="basic-table">
    	<field name="trainingFormId" title="${uiLabelMap.CommonId}" title-style="asterisk" required-field="true"><text/></field>
    	<field name="description" title="${uiLabelMap.HROlbiusTrainingFormDescription}" title-style="asterisk" required-field="true"><text/></field>
    	<field name="submitButton" title="${uiLabelMap.CommonCreate}" widget-style="btn btn-small btn-primary"><submit button-type="button" image-location="icon-ok"/></field>
    </form>
    <form name="listTrainingForm" type="multi" target="updateTrainingForm" odd-row-style="alternate-row" header-row-style="header-row-2"
    	default-table-style="table table-striped table-hover table-bordered dataTable">
    	<actions>
    		<entity-condition entity-name="TrainingForm"><order-by field-name="trainingFormId"/></entity-condition>
    	</actions>
    <field name="trainingFormId" title="${uiLabelMap.CommonId}" ><display/></field>
    <field name="description" title="${uiLabelMap.HROlbiusTrainingFormDescription}"><text/></field>
   	<field name="deletelink" title="${uiLabelMap.CommonDelete}" widget-style="btn btn-mini btn-danger icon-trash">
   		<hyperlink target="deleteTrainingForm" also-hidden="false" description=" " confirmation-message="${uiLabelMap.NotifyDelete}" request-confirmation="true">
   			<parameter param-name="trainingFormId"/>
   		</hyperlink>
   	</field>
    <field name="submitButton" title="${uiLabelMap.CommonUpdate}" widget-style="btn btn-small btn-primary btn-position-center"><submit button-type="button" image-location="icon-ok"/></field>
    </form>
     <!-- Training Type -->
     <form name="AddTrainingType" type="single" target="createTrainingType" header-row-style="header-row" default-table-style="basic-table">
    	<field name="trainingTypeId" title="${uiLabelMap.CommonId}" required-field="true" title-style="asterisk"><text/></field>
    	<field name="description" title="${uiLabelMap.HROlbiusTrainingTypeDescription}" title-style="asterisk" required-field="true"><text/></field>
    	<field name="submitButton" title="${uiLabelMap.CommonCreate}" widget-style="btn btn-small btn-primary"><submit button-type="button" image-location="icon-ok"/></field>
    </form>
    <form name="listTrainingType" type="multi" target="updateTrainingType" odd-row-style="alternate-row" header-row-style="header-row-2"
    	default-table-style="table table-striped table-hover table-bordered dataTable">
    	<actions>
    		<entity-condition entity-name="TrainingType"><order-by field-name="trainingTypeId"/></entity-condition>
    	</actions>
    <field name="trainingTypeId" title="${uiLabelMap.CommonId}" ><display/></field>
    <field name="description" title="${uiLabelMap.HROlbiusTrainingTypeDescription}"><text/></field>
   	<field name="deletelink" title="${uiLabelMap.CommonDelete}" widget-style="btn btn-mini btn-danger icon-trash">
   		<hyperlink target="deleteTrainingType" also-hidden="false" description=" " confirmation-message="${uiLabelMap.NotifyDelete}" request-confirmation="true">
   			<parameter param-name="trainingTypeId"/>
   		</hyperlink>
   	</field>
    <field name="submitButton" title="${uiLabelMap.CommonUpdate}" widget-style="btn btn-small btn-primary btn-position-center"><submit button-type="button" image-location="icon-ok"/></field>
    </form>
    
     <!-- Type Propose -->
     <form name="AddTypePropose" type="single" target="createTypePropose" header-row-style="header-row" default-table-style="basic-table">
    	<field name="typeProposeId" title="${uiLabelMap.HROlbiusTypeProposeID}"><text/></field>
    	<field name="description" title="${uiLabelMap.HROlbiusTypeProposeDescription}" tooltip="${uiLabelMap.CommonRequired}" widget-style="required"><text/></field>
    	<field name="submitButton" title="${uiLabelMap.CommonCreate}" widget-style="btn btn-small btn-primary"><submit button-type="button" image-location="icon-ok"/></field>
    </form>
    <form name="listTypePropose" type="multi" target="updateTypePropose" odd-row-style="alternate-row" header-row-style="header-row-2"
    	default-table-style="table table-striped table-hover table-bordered dataTable">
    	<actions>
    		<entity-condition entity-name="TypePropose"><order-by field-name="typeProposeId"/></entity-condition>
    	</actions>
    <field name="typeProposeId" title="${uiLabelMap.HROlbiusTypeProposeID}"><display/></field>
    <field name="description" title="${uiLabelMap.HROlbiusTypeProposeDescription}"><text/></field>
   	<field name="deletelink" title="${uiLabelMap.CommonDelete}" widget-style="btn btn-mini btn-danger icon-trash">
   		<hyperlink target="deleteTypePropose" also-hidden="false" description=" " confirmation-message="${uiLabelMap.NotifyDelete}" request-confirmation="true">
   			<parameter param-name="typeProposeId"/>
   		</hyperlink>
   	</field>
    <field name="submitButton" title="${uiLabelMap.CommonUpdate}" widget-style="btn btn-small btn-primary btn-position-center"><submit button-type="button" image-location="icon-ok"/></field>
    </form>
    <!-- Marital Status  -->
     <form name="AddMaritalStatus" type="single" target="createMaritalStatus" header-row-style="header-row" default-table-style="basic-table">
    	<field name="maritalStatusId" title="${uiLabelMap.CommonId}" title-style="asterisk" required-field="true"><text/></field>
    	<field name="description" title="${uiLabelMap.HROlbiusTypeProposeDescription}" title-style="asterisk" required-field="true"><text/></field>
    	<field name="submitButton" title="${uiLabelMap.CommonCreate}" widget-style="btn btn-small btn-primary"><submit button-type="button" image-location="icon-ok"/></field>
    </form>
    
    <form name="listMaritalStatus" type="multi" target="updateMaritalStatus" odd-row-style="alternate-row" header-row-style="header-row-2"
    	default-table-style="table table-striped table-hover table-bordered dataTable" paginate-target="EditMaritalStatus">
    	<actions>
    		<entity-condition entity-name="MaritalStatus"><order-by field-name="maritalStatusId"/></entity-condition>
    	</actions>
    <field name="maritalStatusId" title="${uiLabelMap.CommonId}"><display/></field>
    <field name="description" title="${uiLabelMap.HROlbiusTypeProposeDescription}"><text/></field>
   	<field name="deletelink" title="${uiLabelMap.CommonDelete}" widget-style="btn btn-mini btn-danger icon-trash">
   		<hyperlink target="deleteMaritalStatus" also-hidden="false" description=" " confirmation-message="${uiLabelMap.NotifyDelete}" request-confirmation="true">
   			<parameter param-name="maritalStatusId"/>
   		</hyperlink>
   	</field>
    <field name="submitButton" title="${uiLabelMap.CommonUpdate}" widget-style="btn btn-small btn-primary btn-position-center"><submit button-type="button" image-location="icon-ok"/></field>
    </form>
    
    <!-- Family Background -->
     <form name="AddFamilyBackground" type="single" target="createFamilyBackground" header-row-style="header-row" default-table-style="basic-table">
    	<field name="familyBackgroundId" title="${uiLabelMap.CommonId}" title-style="asterisk" required-field="true"><text/></field>
    	<field name="description" title="${uiLabelMap.HROlbiusTypeProposeDescription}" title-style="asterisk" required-field="true"><text/></field>
    	<field name="submitButton" title="${uiLabelMap.CommonCreate}" widget-style="btn btn-small btn-primary"><submit button-type="button" image-location="icon-ok"/></field>
    </form>
    <form name="listFamilyBackground" type="multi" target="updateFamilyBackground" odd-row-style="alternate-row" header-row-style="header-row-2"
    	default-table-style="table table-striped table-hover table-bordered dataTable" paginate-target="EditFamilyBackgroundGlobal">
    	<actions>
    		<entity-condition entity-name="FamilyBackground"><order-by field-name="familyBackgroundId"/></entity-condition>
    	</actions>
    <field name="familyBackgroundId" title="${uiLabelMap.CommonId}"><display/></field>
    <field name="description" title="${uiLabelMap.HROlbiusTypeProposeDescription}"><text/></field>
   	<field name="deletelink" title="${uiLabelMap.CommonDelete}" widget-style="btn btn-mini btn-danger icon-trash">
   		<hyperlink target="deleteFamilyBackground" also-hidden="false" description=" " confirmation-message="${uiLabelMap.NotifyDelete}" request-confirmation="true"> 
   			<parameter param-name="familyBackgroundId"/>
   		</hyperlink>
   	</field>
    <field name="submitButton" title="${uiLabelMap.CommonUpdate}" widget-style="btn btn-small btn-primary btn-position-center"><submit button-type="button" image-location="icon-ok"/></field>
    </form>
    <!-- Personal Background -->
     <form name="AddPersonalBackground" type="single" target="createPersonalBackground" header-row-style="header-row" default-table-style="basic-table">
    	<field name="personalBackgroundId" title="${uiLabelMap.CommonId}" required-field="true" title-style="asterisk"><text/></field>
    	<field name="description" title="${uiLabelMap.HROlbiusTypeProposeDescription}" title-style="asterisk" required-field="true"><text/></field>
    	<field name="submitButton" title="${uiLabelMap.CommonCreate}" widget-style="btn btn-small btn-primary"><submit button-type="button" image-location="icon-ok"/></field>
    </form>
    <form name="listPersonalBackground" type="multi" target="updatePersonalBackground" odd-row-style="alternate-row" header-row-style="header-row-2"
    	default-table-style="table table-striped table-hover table-bordered dataTable">
    	<actions>
    		<entity-condition entity-name="PersonalBackground"><order-by field-name="personalBackgroundId"/></entity-condition>
    	</actions>
    <field name="personalBackgroundId" title="${uiLabelMap.CommonId}" ><display/></field>
    <field name="description" title="${uiLabelMap.HROlbiusTypeProposeDescription}"><text/></field>
   	<field name="deletelink" title="${uiLabelMap.CommonDelete}" widget-style="btn btn-mini btn-danger icon-trash">
   		<hyperlink target="deletePersonalBackground" also-hidden="false" description=" " confirmation-message="${uiLabelMap.NotifyDelete}" request-confirmation="true">
   			<parameter param-name="personalBackgroundId"/>
   		</hyperlink>
   	</field>
    <field name="submitButton" title="${uiLabelMap.CommonUpdate}" widget-style="btn btn-small btn-primary btn-position-center"><submit button-type="button" image-location="icon-ok"/></field>
    </form>
     <!-- Ethnic Origin -->
     <form name="AddEthnicOrigin" type="single" target="createEthnicOrigin" header-row-style="header-row" default-table-style="basic-table">
    	<field name="ethnicOriginId" title="${uiLabelMap.CommonId}" required-field="true" title-style="asterisk"><text/></field>
    	<field name="description" title="${uiLabelMap.HROlbiusTypeProposeDescription}" title-style="asterisk" required-field="true"><text/></field>
    	<field name="submitButton" title="${uiLabelMap.CommonCreate}" widget-style="btn btn-small btn-primary"><submit button-type="button" image-location="icon-ok"/></field>
    </form>
    
    <form name="listEthnicOrigin" type="multi" target="updateEthnicOrigin" odd-row-style="alternate-row" header-row-style="header-row-2"
    	default-table-style="table table-striped table-hover table-bordered dataTable">
    	<actions>
    		<entity-condition entity-name="EthnicOrigin"><order-by field-name="ethnicOriginId"/></entity-condition>
    	</actions>
    <field name="ethnicOriginId" title="${uiLabelMap.CommonId}"><display/></field>
    <field name="description" title="${uiLabelMap.HROlbiusTypeProposeDescription}"><text/></field>
   	<field name="deletelink" title="${uiLabelMap.CommonDelete}" widget-style="btn btn-mini btn-danger icon-trash">
   		<hyperlink target="deleteEthnicOrigin" also-hidden="false" description=" " confirmation-message="${uiLabelMap.NotifyDelete}" request-confirmation="true">
   			<parameter param-name="ethnicOriginId"/>
   		</hyperlink>
   	</field>
    <field name="submitButton" title="${uiLabelMap.CommonUpdate}" widget-style="btn btn-small btn-primary btn-position-center"><submit button-type="button" image-location="icon-ok"/></field>
    </form>
    
     <!-- Religion -->
     <form name="AddReligion" type="single" target="createReligion" header-row-style="header-row" default-table-style="basic-table">
    	<field name="religionId" title="${uiLabelMap.CommonId}" required-field="true" title-style="asterisk"><text/></field>
    	<field name="description" title="${uiLabelMap.HROlbiusTypeProposeDescription}" title-style="asterisk" required-field="true"><text/></field>
    	<field name="submitButton" title="${uiLabelMap.CommonCreate}" widget-style="btn btn-small btn-primary"><submit button-type="button" image-location="icon-ok"/></field>
    </form>
    
    <form name="listReligion" type="multi" target="updateReligion" odd-row-style="alternate-row" header-row-style="header-row-2"
    	default-table-style="table table-striped table-hover table-bordered dataTable">
    	<actions>
    		<entity-condition entity-name="Religion"><order-by field-name="religionId"/></entity-condition>
    	</actions>
    <field name="religionId" title="${uiLabelMap.CommonId}" ><display/></field>
    <field name="description" title="${uiLabelMap.HROlbiusTypeProposeDescription}"><text/></field>
   	<field name="deletelink" title="${uiLabelMap.CommonDelete}" widget-style="btn btn-mini btn-danger icon-trash">
   		<hyperlink target="deleteReligion" also-hidden="false" description=" " confirmation-message="${uiLabelMap.NotifyDelete}" request-confirmation="true">
   			<parameter param-name="religionId"/>
   		</hyperlink>
   	</field>
    <field name="submitButton" title="${uiLabelMap.CommonUpdate}" widget-style="btn btn-small btn-primary btn-position-center"><submit button-type="button" image-location="icon-ok"/></field>
    </form>
    <!-- Nationality -->
     <form name="AddNationality" type="single" target="createNationality" header-row-style="header-row" default-table-style="basic-table">
    	<field name="nationalityId" title="${uiLabelMap.CommonId}" title-style="asterisk" required-field="true"><text/></field>
    	<field name="description" title="${uiLabelMap.HROlbiusTypeProposeDescription}" title-style="asterisk" required-field="true"><text/></field>
    	<field name="submitButton" title="${uiLabelMap.CommonCreate}" widget-style="btn btn-small btn-primary"><submit button-type="button" image-location="icon-ok"/></field>
    </form>
    <form name="listNationality" type="multi" target="updateNationality" odd-row-style="alternate-row" header-row-style="header-row-2"
    	default-table-style="table table-striped table-hover table-bordered dataTable" paginate-target="EditNationality">
    	<actions>
    		<entity-condition entity-name="Nationality"><order-by field-name="nationalityId"/></entity-condition>
    	</actions>
    <field name="nationalityId" title="${uiLabelMap.CommonId}" ><display/></field>
    <field name="description" title="${uiLabelMap.HROlbiusTypeProposeDescription}"><text/></field>
   	<field name="deletelink" title="${uiLabelMap.CommonDelete}" widget-style="btn btn-mini btn-danger icon-trash">
   		<hyperlink target="deleteNationality" also-hidden="false" description=" " confirmation-message="${uiLabelMap.NotifyDelete}" request-confirmation="true">
   			<parameter param-name="nationalityId"/>
   		</hyperlink>
   	</field>
    <field name="submitButton" title="${uiLabelMap.CommonUpdate}" widget-style="btn btn-small btn-primary btn-position-center"><submit button-type="button" image-location="icon-ok"/></field>
    </form>
     <!-- TrainingLevel -->
     <form name="AddTrainingLevel" type="single" target="createTrainingLevel" header-row-style="header-row" default-table-style="basic-table">
    	<field name="trainingLevelId" title="${uiLabelMap.CommonId}" required-field="true" title-style="asterisk"><text/></field>
    	<field name="description" title="${uiLabelMap.HROlbiusTypeProposeDescription}" title-style="asterisk" required-field="true"><text/></field>
    	<field name="submitButton" title="${uiLabelMap.CommonCreate}" widget-style="btn btn-small btn-primary"><submit button-type="button" image-location="icon-ok"/></field>
    </form>
    
    <form name="listTrainingLevel" type="multi" target="updateTrainingLevel" odd-row-style="alternate-row" header-row-style="header-row-2"
    	default-table-style="table table-striped table-hover table-bordered dataTable">
    	<actions>
    		<entity-condition entity-name="TrainingLevel"><order-by field-name="trainingLevelId"/></entity-condition>
    	</actions>
    <field name="trainingLevelId" title="${uiLabelMap.CommonId}" ><display/></field>
    <field name="description" title="${uiLabelMap.HROlbiusTypeProposeDescription}"><text/></field>
   	<field name="deletelink" title="${uiLabelMap.CommonDelete}" widget-style="btn btn-mini btn-danger icon-trash">
   		<hyperlink target="deleteTrainingLevel" also-hidden="false" description=" " confirmation-message="${uiLabelMap.NotifyDelete}" request-confirmation="true">
   			<parameter param-name="trainingLevelId"/>
   		</hyperlink>
   	</field>
    <field name="submitButton" title="${uiLabelMap.CommonUpdate}" widget-style="btn btn-small btn-primary btn-position-center"><submit button-type="button" image-location="icon-ok"/></field>
    </form>
    
    
     <!-- University -->
     <!-- <form name="AddUniversity" type="single" target="createUniversity" header-row-style="header-row" default-table-style="basic-table">
    	<field name="schoolId" title="${uiLabelMap.CommonId}" title-style="asterisk" required-field="true"><text/></field>
    	<field name="schoolName" title="${uiLabelMap.UniversityName}" title-style="asterisk" required-field="true"><text/></field>
    	<field name="geoId" title="${uiLabelMap.CommonCountry}" title-style="asterisk" required-field="true" >
    		<drop-down allow-multiple="false" >
    			<entity-options description="${geoName}" entity-name="Geo">
    				<entity-constraint name="geoTypeId" operator="equals" value="COUNTRY"/>
    			</entity-options>
    		</drop-down>
    	</field>
    	<field name="description" title="${uiLabelMap.HROlbiusTypeProposeDescription}"><text/></field>
    	<field name="submitButton" title="${uiLabelMap.CommonCreate}" widget-style="btn btn-small btn-primary"><submit button-type="button" image-location="icon-ok"/></field>
    </form> -->
    <form name="listUniversity" type="multi" target="updateUniversity" odd-row-style="alternate-row" header-row-style="header-row-2"
    	default-table-style="table table-striped table-hover table-bordered dataTable" paginate-target="EditUniversity" separate-columns="true" group-columns="false">
    	<actions>
    		<entity-condition entity-name="EducationSchool"><order-by field-name="schoolId"/></entity-condition>
    	</actions>
    <field name="schoolId" title="${uiLabelMap.CommonId}"><display/></field>
    <field name="schoolName" title="${uiLabelMap.UniversityName}"><text/></field>
    <field name="description" title="${uiLabelMap.HROlbiusTypeProposeDescription}"><text/></field>
   	<field name="deletelink" title="${uiLabelMap.CommonDelete}" widget-style="btn btn-mini btn-danger icon-trash">
   		<hyperlink target="deleteUniversity" also-hidden="false" description=" " confirmation-message="${uiLabelMap.NotifyDelete}" request-confirmation="true">
   			<parameter param-name="schoolId"/>
   		</hyperlink>
   	</field>
    <field name="submitButton" title="${uiLabelMap.CommonUpdate}" widget-style="btn btn-small btn-primary btn-position-center"><submit button-type="button" image-location="icon-ok"/></field>
    </form>
    <!-- Major -->
     <form name="AddMajor" type="single" target="createMajor" header-row-style="header-row" default-table-style="basic-table">
    	<field name="majorId" title="${uiLabelMap.CommonId}" required-field="true" title-style="asterisk"><text/></field>
    	<field name="description" title="${uiLabelMap.HROlbiusTypeProposeDescription}" title-style="asterisk" required-field="true"><text/></field>
    	<field name="submitButton" title="${uiLabelMap.CommonCreate}" widget-style="btn btn-small btn-primary"><submit button-type="button" image-location="icon-ok"/></field>
    </form>
    <form name="listMajor" type="multi" target="updateMajor" odd-row-style="alternate-row" header-row-style="header-row-2"
    	default-table-style="table table-striped table-hover table-bordered dataTable">
    	<actions>
    		<entity-condition entity-name="Major"><order-by field-name="majorId"/></entity-condition>
    	</actions>
    <field name="majorId" title="${uiLabelMap.CommonId}"><display/></field>
    <field name="description" title="${uiLabelMap.HROlbiusTypeProposeDescription}"><text/></field>
   	<field name="deletelink" title="${uiLabelMap.CommonDelete}" widget-style="btn btn-mini btn-danger icon-trash">
   		<hyperlink target="deleteMajor" also-hidden="false" description=" " confirmation-message="${uiLabelMap.NotifyDelete}" request-confirmation="true">
   			<parameter param-name="majorId"/>
   		</hyperlink>
   	</field>
    <field name="submitButton" title="${uiLabelMap.CommonUpdate}" widget-style="btn btn-small btn-primary btn-position-center"><submit button-type="button" image-location="icon-ok"/></field>
    </form>
    <!-- Grade -->
     <form name="AddGrade" type="single" target="createGrade" header-row-style="header-row" default-table-style="basic-table">
    	<field name="gradeId" title="${uiLabelMap.CommonId}" required-field="true" title-style="asterisk"><text/></field>
    	<field name="description" title="${uiLabelMap.HROlbiusTypeProposeDescription}" title-style="asterisk" required-field="true"><text/></field>
    	<field name="submitButton" title="${uiLabelMap.CommonCreate}" widget-style="btn btn-small btn-primary"><submit button-type="button" image-location="icon-ok"/></field>
    </form>
    <form name="listGrade" type="multi" target="updateGrade" odd-row-style="alternate-row" header-row-style="header-row-2"
    	default-table-style="table table-striped table-hover table-bordered dataTable">
    	<actions>
    		<entity-condition entity-name="Grade"><order-by field-name="gradeId"/></entity-condition>
    	</actions>
    <field name="gradeId" title="${uiLabelMap.CommonId}" ><display/></field>
    <field name="description" title="${uiLabelMap.HROlbiusTypeProposeDescription}"><text/></field>
   	<field name="deletelink" title="${uiLabelMap.CommonDelete}" widget-style="btn btn-mini btn-danger icon-trash">
   		<hyperlink target="deleteGrade" also-hidden="false" description=" " confirmation-message="${uiLabelMap.NotifyDelete}" request-confirmation="true">
   			<parameter param-name="gradeId"/>
   		</hyperlink>
   	</field>
    <field name="submitButton" title="${uiLabelMap.CommonUpdate}" widget-style="btn btn-small btn-primary btn-position-center"><submit button-type="button" image-location="icon-ok"/></field>
    </form>
    <!-- Occupation -->
     <form name="AddOccupation" type="single" target="createOccupation" header-row-style="header-row" default-table-style="basic-table">
    	<field name="occupationId" title="${uiLabelMap.CommonId}" required-field="true" title-style="asterisk"><text/></field>
    	<field name="description" title="${uiLabelMap.HROlbiusTypeProposeDescription}" title-style="asterisk" required-field="true"><text/></field>
    	<field name="submitButton" title="${uiLabelMap.CommonCreate}" widget-style="btn btn-small btn-primary"><submit button-type="button" image-location="icon-ok"/></field>
    </form>
    <form name="listOccupation" type="multi" target="updateOccupation" odd-row-style="alternate-row" header-row-style="header-row-2"
    	default-table-style="table table-striped table-hover table-bordered dataTable">
    	<actions>
    		<entity-condition entity-name="Occupation"><order-by field-name="occupationId"/></entity-condition>
    	</actions>
    <field name="occupationId" title="${uiLabelMap.CommonId}"><display/></field>
    <field name="description" title="${uiLabelMap.HROlbiusTypeProposeDescription}"><text/></field>
   	<field name="deletelink" title="${uiLabelMap.CommonDelete}" widget-style="btn btn-mini btn-danger icon-trash">
   		<hyperlink target="deleteOccupation" also-hidden="false" description=" " confirmation-message="${uiLabelMap.NotifyDelete}" request-confirmation="true">
   			<parameter param-name="occupationId"/>
   		</hyperlink>
   	</field>
    <field name="submitButton" title="${uiLabelMap.CommonUpdate}" widget-style="btn btn-small btn-primary btn-position-center"><submit button-type="button" image-location="icon-ok"/></field>
    </form>
    
      <!-- Punishment Type -->
     <form name="AddPunishmentType" type="single" target="createPunishmentType" header-row-style="header-row" default-table-style="basic-table">
    	<field name="punishmentTypeId" title="${uiLabelMap.CommonId}" title-style="asterisk" required-field="true"><text/></field>
    	<field name="description" title="${uiLabelMap.HROlbiusTypeProposeDescription}" title-style="asterisk" required-field="true"><text/></field>
    	<field name="numberRemindToWarning" title="${uiLabelMap.NumberRemindToWarning}" title-style="asterisk" required-field="true"><text /></field>
    	<field name="submitButton" title="${uiLabelMap.CommonCreate}" widget-style="btn btn-small btn-primary "><submit button-type="button" image-location="icon-ok"/></field>
    </form>
    <form name="listPunishmentType" type="multi" target="updatePunishmentType" odd-row-style="alternate-row" header-row-style="header-row-2"
    	default-table-style="table table-striped table-hover table-bordered dataTable" separate-columns="true" group-columns="false">
    	<actions>
    		<entity-condition entity-name="PunishmentType"><order-by field-name="punishmentTypeId"/></entity-condition>
    	</actions>
    <field name="punishmentTypeId" title="${uiLabelMap.CommonId}"><display/></field>
    <field name="description" title="${uiLabelMap.HROlbiusTypeProposeDescription}"><text/></field>
    <field name="numberRemindToWarning" title="${uiLabelMap.NumberRemindToWarning}" widget-style="abc"><text/></field>
   	<field name="deletelink" title="${uiLabelMap.CommonDelete}" widget-style="btn btn-mini btn-danger icon-trash">
   		<hyperlink target="deletePunishmentType" also-hidden="false" description=" " confirmation-message="${uiLabelMap.NotifyDelete}" request-confirmation="true">
   			<parameter param-name="punishmentTypeId"/>
   		</hyperlink>
   	</field>
    <field name="submitButton" title="${uiLabelMap.CommonUpdate}" widget-style="btn btn-small btn-primary btn-position-center"><submit button-type="button" image-location="icon-ok"/></field>
    </form>
    
    <form name="FindTaxAuthorityRatePayroll" type="single" target="TaxAuthorityRatePayroll" title=""
        header-row-style="header-row" default-table-style="basic-table">
        <field name="noConditionFind"><hidden value="Y"/></field>
        <field name="taxAuthorityRateSeqId" title="${uiLabelMap.HrolbiusTaxAuthorityRateSeqId}"><text-find></text-find></field>
        <field name="name"><text-find></text-find></field>
    	<field name="searchButton" title="${uiLabelMap.CommonFind}" widget-style="btn btn-small btn-primary"><submit button-type="button" image-location="icon-search"/></field>
    </form>
    
    <form name="ListTaxAuthorityRatePayroll" type="list" list-name="listIt" paginate-target="TaxAuthorityRatePayroll" 
    	odd-row-style="alternate-row" header-row-style="header-row-2" default-table-style="table table-hover table-striped table-bordered dataTable">
    	 <actions>
            <set field="entityName" value="TaxAuthorityRatePayroll"/>
            <service service-name="performFind" result-map="result" result-map-list="listIt">
                <field-map field-name="inputFields" from-field="requestParameters"/>
                <field-map field-name="entityName" from-field="entityName"/>
                <field-map field-name="viewIndex" from-field="viewIndex"/>
                <field-map field-name="viewSize" from-field="viewSize"/>
                <field-map field-name="noConditionFind" value="Y"/>
            </service>
        </actions>
        <auto-fields-entity entity-name="TaxAuthorityRatePayroll" default-field-type="display"/>
        <field name="taxAuthorityRateSeqId" title="${uiLabelMap.HrolbiusTaxAuthorityRateSeqId}"
			widget-style="">
			<hyperlink target="AddTaxAuthorityRatePayroll" description="${taxAuthorityRateSeqId}">
				<parameter param-name="taxAuthorityRateSeqId" />
			</hyperlink>
		</field>
		<field name="taxAuthorityRateTypeId" title="${uiLabelMap.taxAuthorityRateTypeId}">
			<display-entity entity-name="TaxAuthorityRateType" description="${description}" key-field-name="taxAuthorityRateTypeId"></display-entity>
		</field>
		<field name="fromValue" title="${uiLabelMap.HrolbiusFromValue}"></field>
		<field name="thruValue" title="${uiLabelMap.HrolbiusThruValue}"></field>
		<field name="fromDate" ><display type="date"></display> </field>
        <field name="deleteLink" title="${uiLabelMap.CommonDelete}"
			widget-style="btn btn-mini btn-danger icon-trash open-sans">
			<hyperlink target="deleteTaxAuthorityRatePayroll" description=" " confirmation-message="${uiLabelMap.NotifyDelete}" request-confirmation="true">
				<parameter param-name="taxAuthorityRateSeqId" />
			</hyperlink>
		</field>
    </form>
    
    <form name="AddTaxAuthorityRatePayroll" type="single" target="UpdateTaxAuthorityRatePayroll">
    	<actions>
    		<entity-one entity-name="TaxAuthorityRatePayroll" value-field="TaxAuthorityRatePayroll"></entity-one>
    		<entity-condition entity-name="PeriodType" list="periodList">
    			<condition-list combine="or">
    				<condition-expr field-name="periodTypeId" operator="equals" value="DAILY"/>
    				<condition-expr field-name="periodTypeId" operator="equals" value="HOURLY"/>
    				<condition-expr field-name="periodTypeId" operator="equals" value="MONTHLY"/>
    				<condition-expr field-name="periodTypeId" operator="equals" value="WEEKLY"/>
    				<condition-expr field-name="periodTypeId" operator="equals" value="YEARLY"/>
    				<condition-expr field-name="periodTypeId" operator="equals" value="QUARTERLY"/>
    			</condition-list>
    		</entity-condition>
    	</actions>
    	<alt-target use-when="TaxAuthorityRatePayroll==null" target="createTaxAuthorityRatePayroll"/>
    	<auto-fields-service service-name="UpdateTaxAuthorityRatePayroll" map-name="TaxAuthorityRatePayroll"/>
    	<field name="taxAuthorityRateSeqId" title="${uiLabelMap.HrolbiusTaxAuthorityRateSeqId}" use-when="TaxAuthorityRatePayroll!=null"><display/></field>
    	<field name="taxAuthorityRateSeqId" use-when="TaxAuthorityRatePayroll==null"><hidden/> </field>
    	<field name="taxAuthGeoId"><hidden value="VNM"/></field>
    	<field name="taxAuthPartyId"><hidden value="VNM_TAX"/></field>
    	<field name="name"><text></text></field>
    	<field name="fromValue" title="${uiLabelMap.HrolbiusFromValue}" required-field="true" title-style="asterisk"></field>
    	<field name="thruValue" title="${uiLabelMap.HrolbiusThruValue}" required-field="true" title-style="asterisk"></field>
    	<field name="taxPercentage" required-field="true" title-style="asterisk"></field>
    	<field name="taxAuthorityRateTypeId" use-when="TaxAuthorityRatePayroll!=null">
    		<display></display>
    	</field>
    	<field name="taxAuthorityRateTypeId"><hidden value="INDIVIDUAL_INC_TAX"/></field>
    	<field name="periodTypeId">
    		<drop-down allow-empty="true">
    			<list-options key-name="periodTypeId" list-name="periodList" description="${description}"/>
    		</drop-down>
    	</field>
    	 <field name="submitButton" use-when="TaxAuthorityRatePayroll==null" title="${uiLabelMap.CommonCreate}" widget-style="btn btn-small btn-primary"><submit button-type="button" image-location="icon-ok"/></field>
        <field name="submitButton" use-when="TaxAuthorityRatePayroll!=null" title="${uiLabelMap.CommonUpdate}" widget-style="btn btn-small btn-primary"><submit button-type="button" image-location="icon-ok"/></field>
    </form>
    
    <form name="ListWorkingShift" type="list" paginate-target="ListWorkingShift" list-name="listIt" odd-row-style="alternate-row" header-row-style="header-row-2" 
    	default-table-style="table table-hover table-striped table-bordered dataTable">
    	<actions>
    		<entity-condition entity-name="WorkingShift" list="listIt" filter-by-date="true">
    			<condition-expr field-name="workingShiftId" operator="not-equals" value="_NA_"/>
    		</entity-condition>
    	</actions>
    	<field name="description" title="${uiLabelMap.WorkingShiftName}">
    		<display></display>
    	</field>
    	<field name="startTime" title="${uiLabelMap.StartTime}">
    		<display></display>
    	</field>
    	<field name="endTime" title="${uiLabelMap.EndTime}">
    		<display></display>
    	</field>
    	<field name="_editLink" title="${uiLabelMap.CommonUpdate}" widget-style="btn btn-mini btn-primary icon-edit">
    		<hyperlink target="EditWorkingShift" description=" ">
				<parameter param-name="workingShiftId" />
			</hyperlink>
    	</field>
    	<field name="deleteLink" title="${uiLabelMap.CommonDelete}"
			widget-style="btn btn-mini btn-danger icon-trash open-sans">
			<hyperlink target="deleteWorkingShift" description=" " confirmation-message="${uiLabelMap.AllWeekWorkLinkWorkShiftWillDelete} ${uiLabelMap.AreYouSure}" request-confirmation="true" >
				<parameter param-name="workingShiftId" />
			</hyperlink>
		</field>
   	</form>
   	
    
   	<form name="ListHolidayInYear" type="list" list-name="listIt" paginate-target="ListHolidayInYear" odd-row-style="alternate-row" header-row-style="header-row-2" 
    	default-table-style="table table-hover table-striped table-bordered dataTable">
    	<actions>
    		
    	</actions>	
    	<field name="holidayTypeId" title="${uiLabelMap.HolidayType}">
    		<display-entity entity-name="HolidayType" description="${description}"></display-entity>
    	</field>
    	<field name="fromDate" title="${uiLabelMap.CommonFromDate}">
    		<display type="date"></display>
    	</field>
    	<field name="thruDate" title="${uiLabelMap.CommonThruDate}" red-when="never">
    		<display type="date"></display>
    	</field>
    	<field name="description" title="${uiLabelMap.CommonDescription}">
    		<display></display>
    	</field>
    	<field name="_editLink" title="${uiLabelMap.CommonUpdate}" widget-style="btn btn-mini btn-primary icon-edit">
    		<hyperlink target="EditHolidayInYear" description=" ">
				<parameter param-name="holidayId"/>
			</hyperlink>
    	</field>
    	<field name="_deleteLink" title="${uiLabelMap.CommonDelete}" widget-style="btn btn-mini btn-danger icon-trash">
    		<hyperlink target="deleteHolidayInYear" description=" " confirmation-message="${uiLabelMap.NotifyDelete}" request-confirmation="true">
				<parameter param-name="holidayId"/>
			</hyperlink>
    	</field>
   	</form>
   	<form name="EditTypeHolidays" type="single" target="updateHolidayTypes">
   		<actions>
   			<entity-one value-field="HolidayType" entity-name="HolidayType"></entity-one>
   		</actions>
 		<alt-target use-when="HolidayType==null" target="createHolidayTypes" />
 		<auto-fields-entity entity-name="HolidayType" default-field-type="edit" map-name="HolidayType"/>
   		<field name="holidayTypeId" title="${uiLabelMap.HrolbiusHolidayTypeId}" use-when="HolidayType==null"><text></text></field>
   		<field name="holidayTypeId" title="${uiLabelMap.HrolbiusHolidayTypeId}" use-when="HolidayType!=null" title-style="asterisk" required-field="true"><display></display> </field>
   		<field name="parentTypeId">
   			<drop-down allow-empty="true">
				<entity-options description="${description}" entity-name="HolidayType" key-field-name="holidayTypeId"></entity-options>
   			</drop-down>
   		</field>
   		<field name="periodTypeId" required-field="true" title-style="asterisk" title="${uiLabelMap.HrolbiusPeriodHolidayTypeId}">
   			<drop-down allow-empty="false">
   				<option key="FISCAL_YEAR" description="${uiLabelMap.HrolbiusPeriodFiscalYear}"/>
   				<option key="FISCAL_QUARTER" description="${uiLabelMap.HrolbiusPeriodFiscalQuarter}"/>
   				<option key="FISCAL_MONTH" description="${uiLabelMap.HrolbiusPeriodFiscalMonth}"/>
   				<option key="FISCAL_WEEK" description="${uiLabelMap.HrolbiusPeriodFiscalWeek}"/>
   			</drop-down>
   		</field>
   		<field name="description" title-style="asterisk" required-field="true"><text></text></field>
   		<field name="submitButton" use-when="HolidayType==null" title="${uiLabelMap.CommonCreate}" widget-style="btn btn-small btn-primary">
   		 	<submit button-type="button" image-location="icon-ok"/>
  		 </field>
  		 <field name="submitButton" use-when="HolidayType!=null" title="${uiLabelMap.CommonUpdate}" widget-style="btn btn-small btn-primary">
   		 	<submit button-type="button" image-location="icon-ok"/>
  		 </field>
   	</form>
   	<form name="ListHolidayTypes" type="list" odd-row-style="alternate-row" list-name="listIt" header-row-style="header-row-2" 
    	default-table-style="table table-hover table-striped table-bordered dataTable">
    	<actions>
    		<entity-condition entity-name="HolidayType" list="listIt"></entity-condition>
    	</actions>
   		<field name="holidayTypeId" title="${uiLabelMap.HrolbiusHolidayTypeId}"><display></display></field>
   		<field name="periodTypeId" title="${uiLabelMap.HrolbiusPeriodHolidayTypeId}">
   			<display-entity entity-name="PeriodType" key-field-name="periodTypeId"></display-entity>
   		</field>
   		<!-- <field name="parentTypeId"><display></display></field> -->
   		<field name="description"><display/></field>
   		<field name="_editLink" title="${uiLabelMap.CommonUpdate}" widget-style="icon-edit open-sans editHolidayTypeBtn" action="updateHolidayType('${holidayTypeId}','${periodTypeId}','${description}')"  event="onclick">
    		<hyperlink target="javascript:void(0);" description=" " url-mode="inter-app" target-type="inter-app">
				<!-- <parameter param-name="holidayTypeId"/> -->
			</hyperlink>
    	</field>
    	<field name="_deleteLink" title="${uiLabelMap.CommonDelete}" widget-style="icon-trash open-sans">
    		<hyperlink target="deleteHolidayTypes" description=" " confirmation-message="${uiLabelMap.NotifyDelete}" request-confirmation="true">
				<parameter param-name="holidayTypeId"/>
			</hyperlink>
    	</field>
   	</form>
   	
   	<form name="EditHolidayInYear" type="single" target="updateHolidayInYear" default-map-name="holidays">
   		<actions>
   			<entity-one value-field="holidays" entity-name="Holidays"></entity-one>
   		</actions>
   		<alt-target use-when="holidays==null" target="createHolidayInYear"/>
   		<field name="holidayId" use-when="holidays!=null">
   			<hidden/>
   		</field>
   		<field name="holidayTypeId" title="${uiLabelMap.HolidayType}">
   			<drop-down>
   				<entity-options description="${description}" entity-name="HolidayType">   					
   				</entity-options>
   			</drop-down>
   		</field>
   		<field name="fromDate" title="${uiLabelMap.CommonFromDate}" required-field="true" title-style="asterisk">
    		<date-time type="date"/>
    	</field>
    	<field name="thruDate" title="${uiLabelMap.CommonThruDate}" required-field="true" title-style="asterisk">
    		<date-time type="date"/>
    	</field>
    	<field name="description">
    		<text></text>
    	</field>
    	<field name="submitButton" use-when="holidays==null" title="${uiLabelMap.CommonCreate}" widget-style="btn btn-small btn-primary">
   		 	<submit button-type="button" image-location="icon-ok"/>
  		 </field>
        <field name="submitButton" use-when="holidays!=null" title="${uiLabelMap.CommonUpdate}" widget-style="btn btn-small btn-primary">
        	<submit button-type="button" image-location="icon-ok"/>
       	</field>
   	</form>
   	
   	<form name="EditWorkingShift" type="single" target="createWorkingShift" default-map-name="workingShift">
   		<actions>
   			<entity-one value-field="workingShift" entity-name="WorkingShift"></entity-one>
   		</actions>
   		<alt-target use-when="workingShift!=null" target="updateWorkingShift"/>
   		<field name="workingShiftId" use-when="workingShift!=null">
   			<hidden/>
   		</field>
   		<field name="description" title="${uiLabelMap.WorkingShiftName}" title-style="asterisk" required-field="true">
   			<text></text>
   		</field>
   		<field name="startTime" title="${uiLabelMap.StartTime}" required-field="true" title-style="asterisk">
			 <text mask="99:99:99"/>
   		</field>
   		<field name="endTime" title="${uiLabelMap.EndTime}" required-field="true" title-style="asterisk">
   			<text mask="99:99:99"/>
   		</field>
   		 <field name="submitButton" use-when="workingShift==null" title="${uiLabelMap.CommonCreate}" widget-style="btn btn-small btn-primary">
   		 	<submit button-type="button" image-location="icon-ok"/>
  		 </field>
        <field name="submitButton" use-when="workingShift!=null" title="${uiLabelMap.CommonUpdate}" widget-style="btn btn-small btn-primary">
        	<submit button-type="button" image-location="icon-ok"/>
       	</field>
   	</form>
    
    <form name="AddDeptPositionType" type="single" target="createDeptPositionType">
    	<field name="partyId" title="${uiLabelMap.FormFieldTitle_partyId}" required-field="true" title-style="asterisk">
    		<lookup target-form-name="LookupPartyName"></lookup>
    	</field>
    	<field name="emplPositionTypeId" title="${uiLabelMap.FormFieldTitle_emplPositionTypeId}">
    		<drop-down>
    			<entity-options entity-name="EmplPositionType" description="${description}">
    				<entity-order-by field-name="description"></entity-order-by>
    			</entity-options>
    		</drop-down>
    	</field>
    	<field name="submitButton" title="${uiLabelMap.CommonCreate}" widget-style="btn btn-small btn-primary"><submit button-type="button" image-location="icon-ok"/></field>
    </form>
    
    <form name="ListDeptPositionType" type="list" group-columns="false" odd-row-style="alternate-row" header-row-style="header-row-2" default-table-style="table table-hover table-striped table-bordered dataTable">
    	<actions>
    		<entity-condition entity-name="DeptPositionType">
    			<order-by field-name="description"></order-by>
    		</entity-condition>
    	</actions>
    	<field name="deptId" title="${uiLabelMap.FormFieldTitle_partyId}" >
    		<display-entity description="${groupName}" key-field-name="partyId" entity-name="PartyGroup">
    		</display-entity>
    	</field>
    	<field name="emplPositionTypeId" title="${uiLabelMap.FormFieldTitle_emplPositionTypeId}">
    		<display-entity description="${description}" entity-name="EmplPositionType">
    		</display-entity>
    	</field>
    	<field name="deletelink" title="${uiLabelMap.CommonDelete}" widget-style="btn btn-mini btn-danger icon-trash">
    		<hyperlink description=" " target="delDeptPositionType" confirmation-message="${uiLabelMap.NotifyDelete}" request-confirmation="true">
    			<parameter param-name="deptId"></parameter>
    			<parameter param-name="emplPositionTypeId"></parameter>
    		</hyperlink>
    	</field>
    </form>
    
    <!-- HUNGNC START EDIT -->
    <form name="ListInternalPurchaseLimit" type="multi" title="" target="updateInternalPurchaseLimit" separate-columns="true"  
		odd-row-style="alternate-row" header-row-style="header-row-2"
		default-table-style="table table-striped table-hover table-bordered dataTable" >
		<actions>
			<entity-condition entity-name="InternalPurchaseLimit">
				<order-by field-name="emplPositionTypeId" />
			</entity-condition>
		</actions>
		<!-- <auto-fields-service service-name="updateInternalPurchaseLimit"
			default-field-type="hidden" /> -->
		<field name="emplPositionTypeId" title="${uiLabelMap.CommonEmplPositionTypeId}">
			<!-- <display /> -->
			<display-entity entity-name="EmplPositionType" description="${description}"></display-entity>
		</field>
		<field name="amountLimit" title="${uiLabelMap.AmountLimit}">
			<text />
		</field>
		<field name="amountLimitRemain" title="${uiLabelMap.AmountLimitRemain}"  required-field="true">
			<text />
		</field>
		<field name="internalPurchasePrice" title="${uiLabelMap.InternalPurchasePrice} ${uiLabelMap.InternalPurchasePriceCalculated}">
			<text />
		</field>
		<field name="deleteLink" title="${uiLabelMap.CommonDelete}"
			widget-style="btn btn-mini btn-danger icon-trash">
			<hyperlink target="deleteInternalPurchaseLimit" description=" ${uiLabelMap.CommonDelete}"
				also-hidden="false" confirmation-message="${uiLabelMap.NotifyDelete}" request-confirmation="true">
				<parameter param-name="emplPositionTypeId" />
			</hyperlink>
		</field>
		<field name="_rowSubmit" title="${uiLabelMap.CommonSelect}">
			<hidden value="Y" />
		</field>
		<field name="submitButton" title="${uiLabelMap.CommonUpdate}"
			widget-style="btn btn-small btn-primary">
			<submit button-type="button" image-location="icon-ok" />
		</field>
	</form>
	
	<form name="AddInternalPurchaseLimit" type="single" target="createInternalPurchaseLimit"
		default-map-name="internalPurchaseLimit" header-row-style="header-row"
		default-table-style="basic-table">
		<!-- <auto-fields-service service-name="createInternalPurchaseLimit"
			default-field-type="hidden" /> -->
		<field name="emplPositionTypeId" title="${uiLabelMap.CommonEmplPositionTypeId}" title-style="asterisk" required-field="true">
			<drop-down>
    			<entity-options entity-name="EmplPositionType" description="${description}">
    				<entity-order-by field-name="description"></entity-order-by>
    			</entity-options>
    		</drop-down>
		</field>
		<field name="amountLimit" title="${uiLabelMap.AmountLimit}"
			title-style="asterisk" required-field="true">
			<text />
		</field>
		<field name="amountLimitRemain" title="${uiLabelMap.AmountLimitRemain}"  required-field="true">
			<text />
		</field>
		<field name="internalPurchasePrice" title="${uiLabelMap.InternalPurchasePrice} :   ${uiLabelMap.InternalPurchasePriceCalculated}" 
			title-style="asterisk" required-field="true">
			<text></text>
		</field>
		<field name="submitButton" title="${uiLabelMap.CommonCreate}"
			widget-style="btn btn-small btn-primary">
			<submit button-type="button" image-location="icon-ok" />
		</field>
	</form>
	<!-- HUNGNC END EDIT -->
    <form name="EditHealthCareProvider" type="single" target="createHealthCareProvider">
    	<field name="groupName" title="${uiLabelMap.HealthCareProviderName}" title-style="asterisk" required-field="true">
    		<text></text>
    	</field>
    	<field name="countryGeoId" title="${uiLabelMap.HRCommonNational}">
    		<drop-down no-current-selected-key="${defaultCountryGeoId}">
                <entity-options entity-name="Geo" key-field-name="geoId" description="${geoId}: ${geoName}">
                    <entity-constraint name="geoTypeId" value="COUNTRY"/>
                    <entity-order-by field-name="geoId"/>
                </entity-options>
            </drop-down>
    	</field>
    	<field name="stateProvinceGeoId" title="${uiLabelMap.CommonState}/${uiLabelMap.CommonCity}" widget-style="required">
    		<drop-down allow-empty="false"/>
   		</field>
    	<field name="submitButton" title="${uiLabelMap.CommonCreate}"
			widget-style="btn btn-small btn-primary">
			<submit button-type="button" image-location="icon-ok" />
		</field>
    </form>
    <form name="ListHealthCareProvider" type="multi" title="" target="updateHealthCareProvider"
		odd-row-style="alternate-row" header-row-style="header-row-2"
		default-table-style="table table-striped table-hover table-bordered dataTable" paginate-target="editHealthCareProvider">
		<actions>
			<entity-condition entity-name="PartyRoleAndContactMechDetail" filter-by-date="true">
				<condition-list>
					<condition-expr field-name="roleTypeId" value="HEALTH_CARE_PROVIDER"/>
				</condition-list>
				<order-by field-name="groupName"/>
			</entity-condition>
		</actions>
		<row-actions>
			<set field="countryGeo" value="${groovy: delegator.findOne(&quot;Geo&quot;, org.ofbiz.base.util.UtilMisc.toMap(&quot;geoId&quot;, paCountryGeoId), false)}" type="Object"/>
			<set field="stateGeo" value="${groovy: delegator.findOne(&quot;Geo&quot;, org.ofbiz.base.util.UtilMisc.toMap(&quot;geoId&quot;, paStateProvinceGeoId), false)}" type="Object"/>
			<set field="postalAddress" value="${groovy: if(stateGeo != null &amp;&amp; countryGeo != null) return stateGeo.geoName + &quot;,&quot; + countryGeo.geoName}"/>
		</row-actions>
		<field name="contactMechId" >
			<hidden/>
		</field>
		<field name="partyId" title="${uiLabelMap.HealthCareProviderName}" >
			<display-entity entity-name="PartyGroup" description="${groupName} [${partyId}]"></display-entity>
		</field>	
		<field name="postalAddress" title="${uiLabelMap.CommonAddress}">
			<display></display>
		</field>	
		<field name="_editLink" title="${uiLabelMap.CommonEdit}" widget-style="icon-edit open-sans" event="onclick" action="editPartyHelthCareProvider('${partyId}', '${contactMechId}', '${groupName}', '${paCountryGeoId}', '${paStateProvinceGeoId}')" >
    		<hyperlink description=" " target="#" target-type="inter-app" also-hidden="false" link-type="anchor" url-mode="inter-app">				
			</hyperlink>
    	</field>
		<field name="_deleteLink" title="${uiLabelMap.CommonDelete}" widget-style="icon-trash open-sans">
    		<hyperlink target="delete" description=" " confirmation-message="${uiLabelMap.NotifyDelete}" request-confirmation="true">
				<parameter param-name="partyId"/>
				<parameter param-name="contactMechId"/>
			</hyperlink>
    	</field>
	</form>
</forms>